jashu_prob_distributions/Binomialdistribution.py
jashu_prob_distributions/Gaussiandistribution.py
jashu_prob_distributions/Generaldistribution.py
jashu_prob_distributions/__init__.py
Jashu_prob_distributions-1.0.4.dist-info/METADATA
Jashu_prob_distributions-1.0.4.dist-info/WHEEL
Jashu_prob_distributions-1.0.4.dist-info/top_level.txt
Jashu_prob_distributions-1.0.4.dist-info/RECORD
