Metadata-Version: 2.1
Name: Jashu-prob-distributions
Version: 1.0.4
Summary: A Python package to get Gaussian distributions and Binominal distributions.
Home-page: https://github.com/Jashwanth-Gowda-R/jashu-prob-distributions.git
Author: Jashwanth Gowda R
Author-email: jashwanth.go@gmail.com
License: MIT
Platform: UNKNOWN
Classifier: License :: OSI Approved :: MIT License
Classifier: Programming Language :: Python :: 3
Classifier: Programming Language :: Python :: 3.7
